pybl/__init__.py
pybl/__main__.py
pybl/models/__init__.py
pybl/models/basemodel.py
pybl/models/blrprx.py
pybl/py.typed
pybl/raincell/__init__.py
pybl/raincell/rcimodel.py
pybl/raincell/storm.py
pybl/timeseries/__init__.py
pybl/timeseries/indexsnapshot.py
pybl/utils/__init__.py
pybl/utils/generate.py
pybl/utils/statistics.py
pyblrp-1.0.1.dist-info/METADATA
pyblrp-1.0.1.dist-info/WHEEL
pyblrp-1.0.1.dist-info/RECORD
