Metadata-Version: 2.1
Name: pyBLRP
Version: 1.0.1
Summary: Python implementation of the Bartlett-Lewis based model for rainfall simulation
Author: Kilin
Author-email: jack233924@gmail.com
Requires-Python: >=3.9,<4.0
Classifier: Programming Language :: Python :: 3
Classifier: Programming Language :: Python :: 3.9
Classifier: Programming Language :: Python :: 3.10
Classifier: Programming Language :: Python :: 3.11
Classifier: Programming Language :: Python :: 3.12
Requires-Dist: numba (>=0.60.0,<0.61.0)
Requires-Dist: numpy (>=1.20.2,<2.0.0)
Requires-Dist: pandas (>=2.1.3,<3.0.0)
Requires-Dist: scipy (>=1.10,<2.0)
